ollamapy/__init__.py
ollamapy/actions.py
ollamapy/analysis_engine.py
ollamapy/chat_session.py
ollamapy/main.py
ollamapy/model_manager.py
ollamapy/ollama_client.py
ollamapy/parameter_utils.py
ollamapy/terminal_interface.py
ollamapy/vibe_report.py
ollamapy/vibe_tests.py
ollamapy-0.8.0.dist-info/METADATA
ollamapy-0.8.0.dist-info/WHEEL
ollamapy-0.8.0.dist-info/entry_points.txt
ollamapy-0.8.0.dist-info/RECORD
