Metadata-Version: 2.4
Name: ollamapy
Version: 0.8.0
Summary: A simple Python package for Ollama utilities with built-in AI vibe tests
Project-URL: Homepage, https://github.com/ScienceIsVeryCool/OllamaPy
Project-URL: Repository, https://github.com/ScienceIsVeryCool/OllamaPy
Project-URL: Issues, https://github.com/ScienceIsVeryCool/OllamaPy/issues
Author-email: The Lazy Artist <TheRealLazyArtist@iCloud.com>
License: GPL-3.0-or-later
Keywords: ai,chat,llama,ollama,python,terminal,utilities,vibe-tests
Classifier: Development Status :: 3 - Alpha
Classifier: Intended Audience :: Developers
Classifier: License :: OSI Approved :: GNU General Public License v3 or later (GPLv3+)
Classifier: Operating System :: OS Independent
Classifier: Programming Language :: Python :: 3
Classifier: Programming Language :: Python :: 3.8
Classifier: Programming Language :: Python :: 3.9
Classifier: Programming Language :: Python :: 3.10
Classifier: Programming Language :: Python :: 3.11
Classifier: Programming Language :: Python :: 3.12
Classifier: Topic :: Scientific/Engineering :: Artificial Intelligence
Classifier: Topic :: Software Development :: Libraries :: Python Modules
Requires-Python: >=3.8
Requires-Dist: requests>=2.25.0
Provides-Extra: dev
Requires-Dist: black; extra == 'dev'
Requires-Dist: isort; extra == 'dev'
Requires-Dist: mypy; extra == 'dev'
Requires-Dist: pytest>=6.0.0; extra == 'dev'
Provides-Extra: test
Requires-Dist: pytest>=6.0.0; extra == 'test'
